environment/__init__.py
environment/asset_management/__init__.py
environment/asset_management/client.py
environment/asset_management/models.py
environment/bathing_waters/__init__.py
environment/bathing_waters/client.py
environment/bathing_waters/models.py
environment/catchment_data/__init__.py
environment/catchment_data/client.py
environment/catchment_data/models.py
environment/flood_monitoring/__init__.py
environment/flood_monitoring/client.py
environment/flood_monitoring/models.py
environment/hydrology/__init__.py
environment/hydrology/client.py
environment/hydrology/models.py
environment/public_register/__init__.py
environment/public_register/client.py
environment/public_register/models.py
environment/rainfall/__init__.py
environment/rainfall/client.py
environment/rainfall/models.py
environment/tide_gauge/__init__.py
environment/tide_gauge/client.py
environment/tide_gauge/models.py
environment/water_quality_data_archive/__init__.py
environment/water_quality_data_archive/client.py
environment/water_quality_data_archive/models.py
environment_client-0.5.13.dist-info/METADATA
environment_client-0.5.13.dist-info/WHEEL
environment_client-0.5.13.dist-info/licenses/LICENSE
environment_client-0.5.13.dist-info/RECORD
