Metadata-Version: 2.4
Name: environment-client
Version: 0.5.13
Summary: Python client for DEFRA's environment.data.gov.uk APIs (typed, async-friendly)
Project-URL: Homepage, https://github.com/cogna-public/environment-client
Project-URL: Bug Tracker, https://github.com/cogna-public/environment-client/issues
Author-email: "Cogna.co" <engineering@cogna.co>
License: MIT License
License-File: LICENSE
Keywords: api,defra,environment,environment.data.gov.uk,flood,hydrology,uk
Classifier: Development Status :: 3 - Alpha
Classifier: Framework :: AsyncIO
Classifier: Intended Audience :: Developers
Classifier: License :: OSI Approved :: MIT License
Classifier: Programming Language :: Python :: 3
Classifier: Programming Language :: Python :: 3.13
Classifier: Topic :: Internet :: WWW/HTTP
Classifier: Typing :: Typed
Requires-Python: >=3.12
Requires-Dist: httpx>=0.28.1
Requires-Dist: pydantic>=2.11.7
Requires-Dist: pyyaml>=6.0.2
